dzdata/__init__.py
dzdata/datafile.py
dzdata/dataset.py
dzdata/dataunit.py
dzdata/field.py
dzdata/fileio.py
dzdata/utils.py
dzdata-0.1.1.dist-info/LICENSE
dzdata-0.1.1.dist-info/METADATA
dzdata-0.1.1.dist-info/WHEEL
dzdata-0.1.1.dist-info/RECORD
